streamlit_canary/__init__.py
streamlit_canary/__main__.py
streamlit_canary/components/__init__.py
streamlit_canary/components/_typing.py
streamlit_canary/components/button.py
streamlit_canary/components/card.py
streamlit_canary/components/column.py
streamlit_canary/components/filelist.py
streamlit_canary/components/input.py
streamlit_canary/components/radio.py
streamlit_canary/components/scope.py
streamlit_canary/components/text.py
streamlit_canary/compositor.py
streamlit_canary/event_handler_no_rerun.py
streamlit_canary/flow.py
streamlit_canary/page.py
streamlit_canary/runner.py
streamlit_canary/session.py
streamlit_canary/wrapper/__init__.py
streamlit_canary/wrapper/base.py
streamlit_canary/wrapper/button.py
streamlit_canary/wrapper/empty.py
streamlit_canary/wrapper/placeholder.py
streamlit_canary/wrapper/radio.py
streamlit_canary-0.1.0.dist-info/METADATA
streamlit_canary-0.1.0.dist-info/WHEEL
streamlit_canary-0.1.0.dist-info/RECORD
